symjax/__init__.py
symjax/_version.py
symjax/base.py
symjax/canonicalization.py
symjax/rl.py
symjax/viz.py
symjax/data/FSDKaggle2018.py
symjax/data/TUTacousticscenes2017.py
symjax/data/__init__.py
symjax/data/audiomnist.py
symjax/data/birdvox_70k.py
symjax/data/birdvox_dcase_20k.py
symjax/data/brain_mnist.py
symjax/data/cars196.py
symjax/data/cassava.py
symjax/data/celeb.py
symjax/data/cifar10.py
symjax/data/cifar100.py
symjax/data/cub200.py
symjax/data/dcase_2019_task4.py
symjax/data/dclde.py
symjax/data/dsprites.py
symjax/data/emnist.py
symjax/data/esc.py
symjax/data/fashionmnist.py
symjax/data/freefield1010.py
symjax/data/groove_MIDI.py
symjax/data/gtzan.py
symjax/data/high_gamma.py
symjax/data/ibeans.py
symjax/data/imagenet.py
symjax/data/imagenette.py
symjax/data/irmas.py
symjax/data/mini.py
symjax/data/mnist.py
symjax/data/patch_camelyon.py
symjax/data/picidae.py
symjax/data/places365_small.py
symjax/data/preprocess.py
symjax/data/rock_paper_scissors.py
symjax/data/seizures_neonatal.py
symjax/data/sonycust.py
symjax/data/speech_commands.py
symjax/data/stl10.py
symjax/data/svhn.py
symjax/data/tinyimagenet.py
symjax/data/univariate_timeseries.py
symjax/data/utils.py
symjax/data/vocalset.py
symjax/data/warblr.py
symjax/data/wavfile.py
symjax/nn/__init__.py
symjax/nn/initializers.py
symjax/nn/layers.py
symjax/nn/losses.py
symjax/nn/ops_nn.py
symjax/nn/optimizers.py
symjax/nn/schedules.py
symjax/probabilities/__init__.py
symjax/probabilities/base.py
symjax/probabilities/pdfs.py
symjax/rl/__init__.py
symjax/rl/ac.py
symjax/rl/agents.py
symjax/rl/ddpg.py
symjax/rl/dqn.py
symjax/rl/example.py
symjax/rl/ppo.py
symjax/rl/utils.py
symjax/tensor/__init__.py
symjax/tensor/base.py
symjax/tensor/control_flow.py
symjax/tensor/fft.py
symjax/tensor/interpolation.py
symjax/tensor/linalg.py
symjax/tensor/normalization.py
symjax/tensor/ops_numpy.py
symjax/tensor/ops_special.py
symjax/tensor/random.py
symjax/tensor/signal.py
symjax-0.5.0.dist-info/LICENSE
symjax-0.5.0.dist-info/METADATA
symjax-0.5.0.dist-info/WHEEL
symjax-0.5.0.dist-info/top_level.txt
symjax-0.5.0.dist-info/RECORD
