Metadata-Version: 2.1
Name: symjax
Version: 0.5.0
Summary: A Symbolic JAX software
Home-page: https://github.com/SymJAX/SymJAX.git
Author: Randall Balestriero
Author-email: randallbalestriero@gmail.com
License: Apache-2.0
Platform: UNKNOWN
Classifier: Natural Language :: English
Classifier: Development Status :: 3 - Alpha
Classifier: Programming Language :: Python :: 3
Classifier: Operating System :: Unix
Requires-Python: >=3.6
Requires-Dist: numpy
Requires-Dist: scipy
Requires-Dist: jax
Requires-Dist: jaxlib
Requires-Dist: networkx
